monnify/__init__.py
monnify/monnify.py
monnify-2.0.0.dist-info/LICENSE
monnify-2.0.0.dist-info/METADATA
monnify-2.0.0.dist-info/WHEEL
monnify-2.0.0.dist-info/top_level.txt
monnify-2.0.0.dist-info/RECORD
