Metadata-Version: 2.1
Name: monnify
Version: 2.0.0
Summary: A Library created for ease of using monnify's API to create unique account numbers for your users/members, verify user transaction, generate Bearer Token etc..
Home-page: https://github.com/ldonjibson/monnify
Author: Olayanju A. Ajibola
Author-email: ajibolaolayanju@gmail.com
License: MIT License
Platform: UNKNOWN
Classifier: Environment :: Web Environment
Classifier: Intended Audience :: Developers
Classifier: License :: OSI Approved :: MIT License
Classifier: Operating System :: OS Independent
Classifier: Programming Language :: Python
Classifier: Programming Language :: Python :: 3
Classifier: Programming Language :: Python :: 3.4
Classifier: Programming Language :: Python :: 3.5
Classifier: Programming Language :: Python :: 3.6
Classifier: Topic :: Internet :: WWW/HTTP
Classifier: Topic :: Internet :: WWW/HTTP :: Dynamic Content
